spotifyaio/__init__.py
spotifyaio/exceptions.py
spotifyaio/models.py
spotifyaio/py.typed
spotifyaio/spotify.py
spotifyaio/util.py
spotifyaio-1.0.0.dist-info/LICENSE.md
spotifyaio-1.0.0.dist-info/METADATA
spotifyaio-1.0.0.dist-info/WHEEL
spotifyaio-1.0.0.dist-info/RECORD
