Metadata-Version: 2.3
Name: spotifyaio
Version: 1.0.0
Summary: Asynchronous Python client for Spotify.
License: MIT
Keywords: Spotify,api,async,client
Author: Joost Lekkerkerker
Author-email: joostlek@outlook.com
Maintainer: Joost Lekkerkerker
Maintainer-email: joostlek@outlook.com
Requires-Python: >=3.12,<4.0
Classifier: Development Status :: 5 - Production/Stable
Classifier: Framework :: AsyncIO
Classifier: Intended Audience :: Developers
Classifier: License :: OSI Approved :: MIT License
Classifier: Natural Language :: English
Classifier: Programming Language :: Python :: 3
Classifier: Programming Language :: Python :: 3.12
Classifier: Programming Language :: Python :: 3.13
Classifier: Topic :: Software Development :: Libraries :: Python Modules
Requires-Dist: aiohttp (>=3.0.0)
Requires-Dist: mashumaro (>=3.11,<4.0)
Requires-Dist: orjson (>=3.9.10,<4.0.0)
Requires-Dist: yarl (>=1.6.0)
Project-URL: Bug Tracker, https://github.com/joostlek/python-spotify/issues
Project-URL: Changelog, https://github.com/joostlek/python-spotify/releases
Project-URL: Documentation, https://github.com/joostlek/python-spotify
Project-URL: Homepage, https://github.com/joostlek/python-spotify
Project-URL: Repository, https://github.com/joostlek/python-spotify
